account_pool_cli/__init__.py
account_pool_cli/cli.py
account_pool_cli-0.1.0.dist-info/licenses/LICENSE
account_pool_cli-0.1.0.dist-info/METADATA
account_pool_cli-0.1.0.dist-info/WHEEL
account_pool_cli-0.1.0.dist-info/entry_points.txt
account_pool_cli-0.1.0.dist-info/top_level.txt
account_pool_cli-0.1.0.dist-info/RECORD
