Metadata-Version: 2.4
Name: account-pool-cli
Version: 0.1.0
Summary: A CLI tool to interact with an account pool service.
Author-email: Swain Zheng <swain.zheng@xxxx.com>
License: MIT License
Project-URL: Homepage, https://github.com/yourusername/account-pool-cli
Project-URL: Bug Tracker, https://github.com/yourusername/account-pool-cli/issues
Classifier: Programming Language :: Python :: 3
Classifier: Operating System :: OS Independent
Classifier: Development Status :: 3 - Alpha
Classifier: Intended Audience :: Developers
Classifier: Topic :: Utilities
Requires-Python: >=3.8
License-File: LICENSE
Requires-Dist: httpx>=0.20
Requires-Dist: fire>=0.4
Dynamic: license-file
